Workbook

Sheet README
B2: AI Credit - Forward Scenario Model
B3: Backs Public Fixed Income section 3. Built 19 Aug 2026.
B5: COLOUR KEY
B6: GREEN - you update | C6: Client / index data. The only cells you need to change.
B7: BLUE - sourced, do not edit | C7: Printed figure from a research PDF. Citation on Sources tab.
B8: YELLOW - judgement | C8: Explicit assumption. Rationale on Sources tab. Change only with a stated reason.
B9: GREY - calculated | C9: Formula. Do not overwrite.
B11: UPDATE ORDER
B12: 1. C0A0 market value (dirty MV, $bn) | C12: Inputs!C6 - currently 9,400 from your Aug-26 read
B13: 2. C0A0 par market value | C13: Inputs!C7 - BLANK. Needed to confirm par vs dirty basis
B14: 3. H0A0 market value ($bn) | C14: Inputs!C27 - currently a back-solve, NOT index data
B15: 4. IG non-AI growth g (low/base/high) | C15: Inputs!C10:C12 - placeholder 3/4/5%. Replace with C0A0 trailing CAGR
B16: 5. HY non-AI growth g | C16: Inputs!C29 - placeholder 3%. Replace with H0A0 trailing CAGR
B18: SENSITIVITY - what moves the answer
B19: C0A0 +/- $1tn | C19: IG 2030 result moves ~1.2pp
B20: IG g from 3% to 5% | C20: IG 2030 result moves ~1.0pp
B21: H0A0 +/- $200bn | C21: HY 2030 result moves ~1.3pp
B22: HY graduation rate 25% -> 80% | C22: Drives the ENTIRE 6-12% HY range. Biggest single unknown in the section.
B24: MODEL IDENTITY (both sleeves)
B25: W2030 = (S0 + N) / ( (D0 - S0) x (1+g)^h + S0 + N )
C26: S0 = W0 x D0 is the current AI stock in the benchmark.
C27: N is NET NEW AI debt retained in that benchmark by end-2030 - not gross issuance.
C28: g applies to the NON-AI remainder only, because AI issuance is itself index growth.
C29: N enters numerator AND denominator: new bonds join the index as well as the cohort.
C30: There is no judgement 'retention' parameter on the IG side. Each route supplies N directly.

Sheet Inputs
B2: INPUTS
B3: Edit GREEN only. Yellow = judgement; change only with a stated reason.
B4: Input | C4: Value | D4: Unit | E4: Status | F4: Source / note
B5: INVESTMENT GRADE
B6: D0 benchmark market value | C6: 9400 | D6: $bn | E6: CLIENT | F6: ICE BofA US Corporate (C0A0), dirty MV, Aug-2026. Reconciles to JPM implied $9.03tn within 4%.
B7: D0 par market value (basis check) | D7: $bn | E7: CLIENT | F7: BLANK - needed to confirm the JPM numerator and C0A0 denominator are on the same basis.
B8: W0 narrow AI cohort weight | C8: 0.062 | D8: % | E8: SOURCED | F8: JPM AI Capex 2.0 p.32. Hyperscalers + data centres + semis. Was 3.9% at end-2024.
B9: h horizon | C9: 4.5 | D9: yrs | E9: SOURCED | F9: 30 Jun 2026 to 31 Dec 2030.
B10: g non-AI growth - low | C10: 0.03 | D10: % | E10: CLIENT | F10: PLACEHOLDER. Replace with C0A0 trailing CAGR.
B11: g non-AI growth - base | C11: 0.04 | D11: % | E11: CLIENT | F11: PLACEHOLDER.
B12: g non-AI growth - high | C12: 0.05 | D12: % | E12: CLIENT | F12: PLACEHOLDER.
B13: Gross 5yr HG AI borrowing | C13: 2100 | D13: $bn | E13: SOURCED | F13: JPM p.32. GLOBAL, USD and non-USD, all wrappers, inclusive of 2026 YTD.
B14: less: issued YTD 2026 | C14: 165 | D14: $bn | E14: SOURCED | F14: JPM p.32, Figure 28 (USD HG market series).
B15: Eligibility factor (Route C) | C15: 0.45 | D15: % | E15: JUDGEMENT | F15: Decomposed from JPM 2026 bridge: $150bn USD HS / $100bn non-USD / $170bn structures / $10bn muni. Band 35-55%.
B16: Apollo public-IG absorption ceiling | C16: 1000 | D16: $bn | E16: SOURCED | F16: Apollo Midyear Credit Outlook p.15: 'may be able to absorb less than $1 trillion of that amount through 2030'.
B17: MS capacity rescaled to C0A0 - 14.2% | C17: 898 | D17: $bn | E17: SOURCED | F17: MS Exhibit 11 ($679bn to 14.2%) reproduces on a $7.15tn implied index base with a 6.0% start; rescaled to C0A0.
B18: MS capacity rescaled to C0A0 - 14.5% | C18: 935 | D18: $bn | E18: SOURCED | F18: MS Exhibit 11 ($711bn to 14.5%) on the same basis. Corroborates Apollo's sub-$1tn ceiling independently.
B19: Slowdown case N (Route D) | C19: 500 | D19: $bn | E19: JUDGEMENT | F19: Hyperscaler borrowing peaks 2027 then decays. Apollo p.14; JPM concurs.
... B22: Apollo hyperscaler weight - 2030E | C22: 0.088 | D22: % | E22: SOURCED | F22: Apollo Exhibit 27, 2030 estimate.
B23: S0 current AI stock = W0 x D0 | C23: =C8*C6 | D23: $bn | E23: CALC
B24: Remaining gross (Route C) | C24: =C13-C14 | D24: $bn | E24: CALC
B26: HIGH YIELD
B27: D0 benchmark market value | C27: 1447 | D27: $bn | E27: CLIENT | F27: BACK-SOLVE ($39.8bn / 2.75%). REPLACE WITH H0A0 - this is not index data.
B28: W0 HPC weight | C28: 0.0275 | D28: % | E28: SOURCED | F28: JPM p.36. $39.8bn across 12 issuers. Was 1.07% at end-2025.
B29: g non-AI growth | C29: 0.03 | D29: % | E29: CLIENT | F29: PLACEHOLDER. Replace with H0A0 trailing CAGR.
B30: Cumulative HPC issuance 2026-30 | C30: 350 | D30: $bn | E30: SOURCED | F30: JPM p.36. Bonds AND loans, peak 2027.
B31: less: already issued | C31: 34.2 | D31: $bn | E31: SOURCED | F31: $31.1bn HY bonds YTD plus the $3.1bn CoreWeave loan.
B32: Bond share of remaining | C32: 0.7 | D32: % | E32: JUDGEMENT | F32: Below JPM's 2026 mix of 81% ($65bn/$80bn): the same note expects loans to fund an increasing share.
B33: Retention - heavy graduation | C33: 0.25 | D33: % | E33: JUDGEMENT | F33: Most 2026-27 vintages upgrade to IG or refinance into ABS.
B34: Retention - moderate (base) | C34: 0.5 | D34: % | E34: JUDGEMENT | F34: Roughly half migrate out of high yield.
B35: Retention - low graduation | C35: 0.8 | D35: % | E35: JUDGEMENT | F35: Matches the OBSERVED 2026 conversion rate. See back-test below.
B36: MS capacity to 15% threshold | C36: 170 | D36: $bn | E36: SOURCED | F36: Morgan Stanley, A Break from the Heat, p.10.
B37: JPM end-2026 waypoint | C37: 0.045 | D37: % | E37: SOURCED | F37: JPM p.40: 'would place the HPC subsector at about 4.5% of the High-Yield Bond index by year-end 2026'.
B38: 2H26 gross HY HPC issuance | C38: 33.9 | D38: $bn | E38: SOURCED | F38: JPM $65bn FY26 forecast less $31.1bn issued YTD.
... B41: HPC gross HY issuance YTD ($bn) | C41: 31.1 | D41: $bn | E41: SOURCED | F41: JPM p.36. 41% of $76.9bn non-refi HY issuance.
B42: S0 current HPC stock = W0 x D0 | C42: =C28*C27 | D42: $bn | E42: CALC
B43: Remaining issuance | C43: =C30-C31 | D43: $bn | E43: CALC

Sheet IG_Scenario
B2: INVESTMENT GRADE - narrow AI cohort at end-2030
B3: Live. Change Inputs and every figure below moves.
B5: Route / scenario | C5: N ($bn) | D5: g low | E5: g base | F5: g high | G5: Basis
B6: D - Demand slowdown (LOW) | C6: =Inputs!C19 | D6: =(Inputs!C23+$C$6)/((Inputs!C6-Inputs!C23)*(1+Inputs!C10)^Inputs!C9+Inputs!C23+$C$6) | E6: =(Inputs!C23+$C$6)/((Inputs!C6-Inputs!C23)*(1+Inputs!C11)^Inputs!C9+Inputs!C23+$C$6) | F6: =(Inputs!C23+$C$6)/((Inputs!C6-Inputs!C23)*(1+Inputs!C12)^Inputs!C9+Inputs!C23+$C$6) | G6: Hyperscaler borrowing peaks 2027 then decays. Apollo p.14.
B7: B - Capex bottom-up (BASE) | C7: see below | D7: =AVERAGE($C$21,$D$21) | E7: =AVERAGE($C$21,$D$21) | F7: =AVERAGE($C$21,$D$21) | G7: Apollo hyperscaler path 4.8% -> 8.8%, extended to data centres and semis. Built below.
B8: C - Gross x eligibility | C8: =Inputs!C24*Inputs!C15 | D8: =(Inputs!C23+$C$8)/((Inputs!C6-Inputs!C23)*(1+Inputs!C10)^Inputs!C9+Inputs!C23+$C$8) | E8: =(Inputs!C23+$C$8)/((Inputs!C6-Inputs!C23)*(1+Inputs!C11)^Inputs!C9+Inputs!C23+$C$8) | F8: =(Inputs!C23+$C$8)/((Inputs!C6-Inputs!C23)*(1+Inputs!C12)^Inputs!C9+Inputs!C23+$C$8) | G8: JPM $2.1tn less $165bn issued, times a 45% decomposed eligibility factor.
B9: A1 - Capacity, MS rescaled low | C9: =Inputs!C17 | D9: =(Inputs!C23+$C$9)/((Inputs!C6-Inputs!C23)*(1+Inputs!C10)^Inputs!C9+Inputs!C23+$C$9) | E9: =(Inputs!C23+$C$9)/((Inputs!C6-Inputs!C23)*(1+Inputs!C11)^Inputs!C9+Inputs!C23+$C$9) | F9: =(Inputs!C23+$C$9)/((Inputs!C6-Inputs!C23)*(1+Inputs!C12)^Inputs!C9+Inputs!C23+$C$9) | G9: MS 14.2% avg non-financial max sector share, rescaled from its $7.15tn implied base to C0A0.
B10: A2 - Capacity, MS rescaled high | C10: =Inputs!C18 | D10: =(Inputs!C23+$C$10)/((Inputs!C6-Inputs!C23)*(1+Inputs!C10)^Inputs!C9+Inputs!C23+$C$10) | E10: =(Inputs!C23+$C$10)/((Inputs!C6-Inputs!C23)*(1+Inputs!C11)^Inputs!C9+Inputs!C23+$C$10) | F10: =(Inputs!C23+$C$10)/((Inputs!C6-Inputs!C23)*(1+Inputs!C12)^Inputs!C9+Inputs!C23+$C$10) | G10: MS 14.5% avg all-sector max share, same basis.
B11: A3 - Capacity ceiling (HIGH) | C11: =Inputs!C16 | D11: =(Inputs!C23+$C$11)/((Inputs!C6-Inputs!C23)*(1+Inputs!C10)^Inputs!C9+Inputs!C23+$C$11) | E11: =(Inputs!C23+$C$11)/((Inputs!C6-Inputs!C23)*(1+Inputs!C11)^Inputs!C9+Inputs!C23+$C$11) | F11: =(Inputs!C23+$C$11)/((Inputs!C6-Inputs!C23)*(1+Inputs!C12)^Inputs!C9+Inputs!C23+$C$11) | G11: Apollo: public IG can absorb 'less than $1 trillion' through 2030. Convergence with A1/A2 is independent.
B12: E - Run-rate persists (STRESS) | C12: =Inputs!C20 | D12: =(Inputs!C23+$C$12)/((Inputs!C6-Inputs!C23)*(1+Inputs!C10)^Inputs!C9+Inputs!C23+$C$12) | E12: =(Inputs!C23+$C$12)/((Inputs!C6-Inputs!C23)*(1+Inputs!C11)^Inputs!C9+Inputs!C23+$C$12) | F12: =(Inputs!C23+$C$12)/((Inputs!C6-Inputs!C23)*(1+Inputs!C12)^Inputs!C9+Inputs!C23+$C$12) | G12: 2026 issuance pace simply continues. See run-rate tension in section 3.3.
B14: ROUTE B - capex bottom-up, two constructions
B15: B1 weight ratio W0 x (8.8% / 4.8%) | C15: =Inputs!C8*Inputs!C22/Inputs!C21 | G15: Applies Apollo's hyperscaler multiple to the narrow cohort. Assumes DC+semis scale identically.
B16: B2 hyperscaler stock today | C16: =Inputs!C21*Inputs!C6
B17: non-hyperscaler index grown at g base | C17: =(Inputs!C6-C16)*(1+Inputs!C11)^Inputs!C9
B18: implied net new hyperscaler debt to reach 8.8% | C18: =(Inputs!C22*(C17+C16)-C16)/(1-Inputs!C22)
B19: DC + semis today, scaled by the same multiple | C19: =(Inputs!C23-C16)*Inputs!C22/Inputs!C21
B20: narrow cohort 2030 (B2) | C20: =(C16+C18+C19)/(C17+C16+C18+C19)
B21: ROUTE B RANGE (low / high) | C21: =MIN(C15,C20) | D21: =MAX(C15,C20) | G21: Reported in the note as 'approximately 11%'.
B23: HEADLINE - IG
B24: Current (W0) | C24: =Inputs!C8
B25: Low (Route D, g base) | C25: =E6
B26: Base (Route B) | C26: =AVERAGE(C21,D21)
B27: High (Route A, g base) | C27: =E11
B28: Stress (Route E, g base) | C28: =E12

Sheet HY_Scenario
B2: HIGH YIELD - HPC cohort at end-2030
B3: Graduation to IG / ABS is the dominant unknown. No source quantifies it.
B5: Scenario | C5: Retention | D5: N ($bn) | E5: 2030 weight | F5: Basis
B6: Heavy graduation (LOW) | C6: =Inputs!C33 | D6: =Inputs!C43*Inputs!C32*Inputs!C33 | E6: =(Inputs!C42+D6)/((Inputs!C27-Inputs!C42)*(1+Inputs!C29)^Inputs!C9+Inputs!C42+D6) | F6: Most 2026-27 vintages upgrade or refinance into ABS / IG.
B7: Moderate (BASE) | C7: =Inputs!C34 | D7: =Inputs!C43*Inputs!C32*Inputs!C34 | E7: =(Inputs!C42+D7)/((Inputs!C27-Inputs!C42)*(1+Inputs!C29)^Inputs!C9+Inputs!C42+D7) | F7: Roughly half migrate out of high yield.
B8: Low graduation (HIGH) | C8: =Inputs!C35 | D8: =Inputs!C43*Inputs!C32*Inputs!C35 | E8: =(Inputs!C42+D8)/((Inputs!C27-Inputs!C42)*(1+Inputs!C29)^Inputs!C9+Inputs!C42+D8) | F8: Migration matches the observed 2026 conversion rate.
B10: CROSS-CHECK - MS capacity to 15% | D10: =Inputs!C36 | E10: =(Inputs!C42+D10)/((Inputs!C27-Inputs!C42)*(1+Inputs!C29)^Inputs!C9+Inputs!C42+D10) | F10: MS sized $170bn to reach ~15% on their own base. Not binding on any case above.
B12: BACK-TEST vs JPM's published end-2026 waypoint
B13: Any credible retention must reproduce 4.5% at YE26. The prior 40-60% assumption did not.
B14: Retention on 2H26 gross | D14: N ($bn) | E14: Implied YE26 weight
B15: 0.25 | D15: =Inputs!C38*0.25 | E15: =(Inputs!C42+D15)/((Inputs!C27-Inputs!C42)*(1+Inputs!C29)^0.5+Inputs!C42+D15)
B16: 0.5 | D16: =Inputs!C38*0.5 | E16: =(Inputs!C42+D16)/((Inputs!C27-Inputs!C42)*(1+Inputs!C29)^0.5+Inputs!C42+D16)
B17: 0.75 | D17: =Inputs!C38*0.75 | E17: =(Inputs!C42+D17)/((Inputs!C27-Inputs!C42)*(1+Inputs!C29)^0.5+Inputs!C42+D17)
B18: 0.8 | D18: =Inputs!C38*0.8 | E18: =(Inputs!C42+D18)/((Inputs!C27-Inputs!C42)*(1+Inputs!C29)^0.5+Inputs!C42+D18)
B19: 1 | D19: =Inputs!C38*1.0 | E19: =(Inputs!C42+D19)/((Inputs!C27-Inputs!C42)*(1+Inputs!C29)^0.5+Inputs!C42+D19)
B20: JPM PUBLISHED WAYPOINT | E20: =Inputs!C37 | F20: Retention of 75-80% reproduces this.
B22: OBSERVED 2026 CONVERSION - independent check
B23: HPC stock at end-2025 = W(YE25) x (D0 - 2026 growth) | C23: =Inputs!C39*(Inputs!C27-Inputs!C40)
B24: HPC stock mid-Jun-2026 | C24: =Inputs!C42
B25: Stock change ($bn) | C25: =Inputs!C42-C23
B26: Gross HPC HY issuance YTD ($bn) | C26: =Inputs!C41
B27: IMPLIED CONVERSION RATE | C27: =C25/Inputs!C41 | F27: Caveat: includes issuers newly classified into HPC, so this is an upper read.
B29: HEADLINE - HY
B30: Current (W0) | C30: =Inputs!C28
B31: Low (heavy graduation) | C31: =E6
B32: Base (moderate) | C32: =E7
B33: High (low graduation) | C33: =E8

Sheet Sources
B2: SOURCES - every non-client number in this model
B4: Figure | C4: Value | D4: Document / page | E4: Verification status
B5: Narrow HG AI cohort weight | C5: 6.2% | D5: JPM AI Capex 2.0, 17 Jun 2026, p.32 | E5: VERIFIED against PDF text in research/
B6: same, end-2024 | C6: 3.9% | D6: JPM AI Capex 2.0, p.32 | E6: VERIFIED against PDF text in research/
B7: Wide HG ecosystem | C7: 15.5% / $1.4tn | D7: JPM AI Capex 2.0, p.32 | E7: VERIFIED against PDF text in research/
B8: AI HG issuance YTD 2026 | C8: $165bn | D8: JPM AI Capex 2.0, p.32, Fig 28 (USD series) | E8: VERIFIED against PDF text in research/
B9: 5yr HG AI borrowing | C9: $2.1tn | D9: JPM AI Capex 2.0, p.32 (global, USD + non-USD) | E9: VERIFIED against PDF text in research/
B10: 2026 bridge | C10: 150 / 100 / 170 / 5-15 | D10: JPM AI Capex 2.0, p.32 | E10: VERIFIED against PDF text in research/
B11: USD hyperscaler avg maturity | C11: 17 yrs | D11: JPM AI Capex 2.0, p.34 (non-USD 14 yrs) | E11: VERIFIED against PDF text in research/
B12: HG market vs leveraged finance | C12: 3x | D12: JPM AI Capex 2.0, p.27 | E12: VERIFIED against PDF text in research/
B13: HPC HY weight | C13: 2.75% / $39.8bn / 12 issuers | D13: JPM AI Capex 2.0, p.36 | E13: VERIFIED against PDF text in research/
B14: same, end-2025 | C14: 1.07% | D14: JPM AI Capex 2.0, p.36 | E14: VERIFIED against PDF text in research/
B15: HPC HY issuance YTD | C15: $31.1bn of $76.9bn non-refi | D15: JPM AI Capex 2.0, p.36 | E15: VERIFIED against PDF text in research/
... B49: Five-name USD IG stock | C49: 3% at end-2025 | D49: BoE FSR Jul 2026 | E49: EXTERNAL - not held locally, not verified
B51: NOTE - how the MS capacity figures reconcile
B52: MS Exhibit 11 gives $679bn to reach 14.2% and $711bn to reach 14.5%. Solving each DIRECTLY as
B53: X = I x (t - s) / (1 - t) with a 6.0% start, both reproduce on ONE implied index base of $7.15tn,
B54: to within 0.7%. (Differencing the two points instead is badly conditioned - a 3-in-1000 denominator
B55: against inputs rounded to whole $bn - and produces a spurious $8.4-10.7tn. Do not use that method.)
B56: The $7.15tn base sits below the same note's 'approximately US$10 trillion': that figure describes the
B57: US IG MARKET and its investor base, while the capacity exhibit runs on an INDEX. Both are correct.
B58: Rescaled to C0A0 on the same logic, MS implies $898-935bn - independently corroborating Apollo's
B59: sub-$1tn ceiling from a completely different method (historical sector-share ceilings vs ratings and
B60: single-name limits). This convergence is the strongest quantitative result in the section.

Sheet Data_Needed
B2: DATA STILL REQUIRED
B3: Items 1-4 are yours to supply. Items 5-7 are not available from any source in the workspace.
B5: Input | C5: Cell | D5: Effect on the answer | E5: Status
B6: C0A0 dirty market value, Aug-2026 | C6: Inputs!C6 | D6: +/- $1tn moves IG 2030 by ~1.2pp | E6: RECEIVED - $9.4tn
B7: C0A0 par market value, Aug-2026 | C7: Inputs!C7 | D7: Basis check only, ~0.2pp | E7: OUTSTANDING
B8: H0A0 market value, Aug-2026 | C8: Inputs!C27 | D8: Replaces the $1,447bn back-solve | E8: OUTSTANDING
B9: Largest single-issuer weight in C0A0 | C9: validates C6 | D9: If ~2.3% the universes reconcile; if ~1.9% C0A0 is broader than the index MS/GS quote and the $898-935bn rescaling is overstated | E9: OUTSTANDING - HIGHEST PRIORITY
B10: C0A0 MV time series (3/5/10yr) | C10: Inputs!C10:C12 | D10: g 3% -> 5% moves IG 2030 by ~1.0pp | E10: OUTSTANDING
B11: H0A0 MV time series | C11: Inputs!C29 | D11: Currently held flat at 3% | E11: OUTSTANDING
B12: Cohort constituent list on C0A0 | C12: Inputs!C8 | D12: Would replace JPM's unpublished 6.2% with a computed weight | E12: NOT AVAILABLE from any source
B13: HY graduation rate to IG / ABS | C13: Inputs!C33:C35 | D13: DRIVES THE ENTIRE 6-12% HY RANGE | E13: NOT QUANTIFIED by any source
B14: Deal-level index-eligibility schedule | C14: Inputs!C15 | D14: Would replace the 35-55% eligibility band | E14: NOT AVAILABLE from any source
B17: SUGGESTED PROXIES if items 6-7 cannot be sourced
B18: Graduation rate: count HY -> IG rating migrations for data-centre / HPC issuers over 2026-27 as they occur,
B19: and track ABS/CMBS take-outs of named construction bonds. Two to three quarters of data would bound it.
B20: Eligibility: track the share of each quarter's AI HG issuance that actually enters C0A0 within one month.
B21: This converts the 35-55% band into a measured series within a year.
